piecemaker/__init__.py
piecemaker/_version.py
piecemaker/adjacent.py
piecemaker/base.py
piecemaker/cut_proof.py
piecemaker/distribution.py
piecemaker/lines_svg.py
piecemaker/reduce.py
piecemaker/script.py
piecemaker/tools.py
piecemaker/paths/__init__.py
piecemaker/paths/interlockingnubs.py
piecemaker/paths/stochasticnubs.py
piecemaker-0.8.0.dist-info/METADATA
piecemaker-0.8.0.dist-info/WHEEL
piecemaker-0.8.0.dist-info/entry_points.txt
piecemaker-0.8.0.dist-info/licenses/COPYING
piecemaker-0.8.0.dist-info/licenses/COPYING.LESSER
piecemaker-0.8.0.dist-info/RECORD
