Metadata-Version: 2.4
Name: piecemaker
Version: 0.8.0
Summary: Create jigsaw puzzle pieces from an image
Project-URL: Homepage, https://github.com/jkenlooper/piecemaker
Author-email: Jake Hickenlooper <jake@weboftomorrow.com>
License: LGPLv3+
License-File: COPYING
License-File: COPYING.LESSER
Requires-Python: <4,>=3.9
Requires-Dist: beautifulsoup4
Requires-Dist: future
Requires-Dist: lxml
Requires-Dist: pillow<11,>=8.4.0
Requires-Dist: pixsaw<0.7,>=0.6.0
Requires-Dist: rtree
Requires-Dist: svgwrite>=1.4.1
Provides-Extra: dev
Provides-Extra: test
Requires-Dist: coverage; extra == 'test'
Requires-Dist: pytest; extra == 'test'
